cocotbext/mipi_csi2/__init__.py
cocotbext/mipi_csi2/about.py
cocotbext/mipi_csi2/bus.py
cocotbext/mipi_csi2/config.py
cocotbext/mipi_csi2/exceptions.py
cocotbext/mipi_csi2/packet.py
cocotbext/mipi_csi2/rx.py
cocotbext/mipi_csi2/tx.py
cocotbext/mipi_csi2/utils.py
cocotbext/mipi_csi2/phy/__init__.py
cocotbext/mipi_csi2/phy/cphy.py
cocotbext/mipi_csi2/phy/dphy.py
cocotbext_mipi_csi2-0.2.0.dist-info/licenses/LICENSE
cocotbext_mipi_csi2-0.2.0.dist-info/METADATA
cocotbext_mipi_csi2-0.2.0.dist-info/WHEEL
cocotbext_mipi_csi2-0.2.0.dist-info/top_level.txt
cocotbext_mipi_csi2-0.2.0.dist-info/RECORD
