Metadata-Version: 2.4
Name: cocotbext-mipi-csi2
Version: 0.2.0
Summary: MIPI CSI-2 simulation framework for cocotb
Author-email: David stonelyd <stonelyd@yahoo.com>
License: MIT
Project-URL: Bug Tracker, https://github.com/stonelyd/cocotbext-mipi-csi2/issues
Project-URL: Source Code, https://github.com/stonelyd/cocotbext-mipi-csi2
Project-URL: Documentation, https://cocotbext-mipi-csi2.readthedocs.io/
Keywords: mipi,csi-2,dphy,cphy,camera,cocotb,simulation
Classifier: Development Status :: 3 - Alpha
Classifier: Framework :: cocotb
Classifier: Intended Audience :: Developers
Classifier: Operating System :: OS Independent
Classifier: Programming Language :: Python :: 3
Classifier: Programming Language :: Python :: 3.6
Classifier: Programming Language :: Python :: 3.7
Classifier: Programming Language :: Python :: 3.8
Classifier: Programming Language :: Python :: 3.9
Classifier: Programming Language :: Python :: 3.10
Classifier: Programming Language :: Python :: 3.11
Classifier: Programming Language :: Python :: 3.12
Classifier: Programming Language :: Python :: 3.13
Classifier: Topic :: Scientific/Engineering :: Electronic Design Automation (EDA)
Classifier: Topic :: System :: Hardware
Requires-Python: >=3.6
License-File: LICENSE
Requires-Dist: cocotb>=1.9.0
Requires-Dist: cocotb-bus>=0.2.1
Requires-Dist: numpy>=1.16.0
Provides-Extra: test
Requires-Dist: pytest>=6.0; extra == "test"
Requires-Dist: pytest-cov; extra == "test"
Requires-Dist: cocotb-test>=0.2.4; extra == "test"
Provides-Extra: dev
Requires-Dist: pytest>=6.0; extra == "dev"
Requires-Dist: pytest-cov; extra == "dev"
Requires-Dist: cocotb-test>=0.2.4; extra == "dev"
Requires-Dist: sphinx; extra == "dev"
Requires-Dist: sphinx-rtd-theme; extra == "dev"
Requires-Dist: black; extra == "dev"
Requires-Dist: flake8; extra == "dev"
Requires-Dist: mypy; extra == "dev"
Dynamic: license-file
